PyGeoStudio/Analysis.py
PyGeoStudio/BasePropertiesClass.py
PyGeoStudio/Color.py
PyGeoStudio/Context.py
PyGeoStudio/Dataset.py
PyGeoStudio/Function.py
PyGeoStudio/GeoPath.py
PyGeoStudio/Geometry.py
PyGeoStudio/Material.py
PyGeoStudio/Mesh.py
PyGeoStudio/PyGeoStudio.py
PyGeoStudio/Reinforcement.py
PyGeoStudio/Results.py
PyGeoStudio/__init__.py
PyGeoStudio/builtin_functions.py
PyGeoStudio/utils.py
PyGeoStudio-0.4.3.dist-info/METADATA
PyGeoStudio-0.4.3.dist-info/WHEEL
PyGeoStudio-0.4.3.dist-info/top_level.txt
PyGeoStudio-0.4.3.dist-info/RECORD
