Metadata-Version: 2.1
Name: PyGeoStudio
Version: 0.4.3
Summary: Python library allowing reading/writing GeoStudio .gsz files
Home-page: https://github.com/MoiseRousseau/PyGeoStudio
Author: Moise Rousseau
Author-email: rousseau.moise@gmail.com
Project-URL: Bug Reports, https://github.com/MoiseRousseau/PyGeoStudio/issues
Project-URL: Source, https://github.com/MoiseRousseau/PyGeoStudio/
Project-URL: Documentation, https://pygeostudio.readthedocs.io/
Keywords: Geotechnics,Numerical Simulation,Hydrogeology,Optimization
Classifier: Intended Audience :: Science/Research
Classifier: Topic :: Scientific/Engineering
Classifier: License :: OSI Approved :: GNU General Public License v3 (GPLv3)
Classifier: Programming Language :: Python :: 3
Requires-Python: >=3.6, <4
Requires-Dist: numpy
Requires-Dist: matplotlib
Requires-Dist: plyfile
Requires-Dist: bs4
Requires-Dist: lxml
Requires-Dist: prettytable
